mercylog/__init__.py
mercylog/bashlog-datalog.jar
mercylog/bashlog.py
mercylog/cli.py
mercylog/config/__init__.py
mercylog/config/config.py
mercylog/datahike-0.2.0-beta-standalone.jar
mercylog/lib/__init__.py
mercylog/lib/util.py
mercylog/simple.py
mercylog-0.1.0.dist-info/WHEEL
mercylog-0.1.0.dist-info/METADATA
mercylog-0.1.0.dist-info/RECORD
